{"name":"build-javascript","namedChunkGroups":{"app":{"name":"app","assets":[{"name":"webpack-runtime-fbf658f7276de38b3cd6.js","size":4130},{"name":"framework-f588aba7219f751c192d.js","size":140785},{"name":"styles.c924e38ef16fde5fee3b.css","size":180468},{"name":"app-5d63747bd0c44f02b0c4.js","size":70958}],"filteredAssets":0,"assetsSize":396341,"filteredAuxiliaryAssets":8,"auxiliaryAssetsSize":3910772},"component---src-pages-404-js":{"name":"component---src-pages-404-js","assets":[{"name":"commons-b7fef59dcd5faf54d02b.js","size":40285},{"name":"component---src-pages-404-js-f00800bf8bf1e956ba6a.js","size":770}],"filteredAssets":0,"assetsSize":41055,"filteredAuxiliaryAssets":2,"auxiliaryAssetsSize":168763},"component---src-pages-about-js":{"name":"component---src-pages-about-js","assets":[{"name":"commons-b7fef59dcd5faf54d02b.js","size":40285},{"name":"component---src-pages-about-js-3b3e76109a6681e228ff.js","size":8814}],"filteredAssets":0,"assetsSize":49099,"filteredAuxiliaryAssets":2,"auxiliaryAssetsSize":189668},"component---src-pages-contact-js":{"name":"component---src-pages-contact-js","assets":[{"name":"commons-b7fef59dcd5faf54d02b.js","size":40285},{"name":"component---src-pages-contact-js-cc3f9175753ecb5747a0.js","size":3894}],"filteredAssets":0,"assetsSize":44179,"filteredAuxiliaryAssets":2,"auxiliaryAssetsSize":179611},"component---src-pages-index-js":{"name":"component---src-pages-index-js","assets":[{"name":"1a48c3c1-b61a09652e7a355c26d9.js","size":3372},{"name":"commons-b7fef59dcd5faf54d02b.js","size":40285},{"name":"component---src-pages-index-js-52b8f11538eb0e8afb7a.js","size":4941}],"filteredAssets":0,"assetsSize":48598,"filteredAuxiliaryAssets":3,"auxiliaryAssetsSize":1055592},"component---src-pages-services-js":{"name":"component---src-pages-services-js","assets":[{"name":"commons-b7fef59dcd5faf54d02b.js","size":40285},{"name":"component---src-pages-services-js-dbd479ed996012e3a083.js","size":3062}],"filteredAssets":0,"assetsSize":43347,"filteredAuxiliaryAssets":2,"auxiliaryAssetsSize":175379}},"assetsByChunkName":{"app":["webpack-runtime-fbf658f7276de38b3cd6.js","framework-f588aba7219f751c192d.js","styles.c924e38ef16fde5fee3b.css","app-5d63747bd0c44f02b0c4.js"],"component---src-pages-404-js":["commons-b7fef59dcd5faf54d02b.js","component---src-pages-404-js-f00800bf8bf1e956ba6a.js"],"component---src-pages-about-js":["commons-b7fef59dcd5faf54d02b.js","component---src-pages-about-js-3b3e76109a6681e228ff.js"],"component---src-pages-contact-js":["commons-b7fef59dcd5faf54d02b.js","component---src-pages-contact-js-cc3f9175753ecb5747a0.js"],"component---src-pages-index-js":["1a48c3c1-b61a09652e7a355c26d9.js","commons-b7fef59dcd5faf54d02b.js","component---src-pages-index-js-52b8f11538eb0e8afb7a.js"],"component---src-pages-services-js":["commons-b7fef59dcd5faf54d02b.js","component---src-pages-services-js-dbd479ed996012e3a083.js"]},"childAssetsByChunkName":{}}